beancount_hypothesis/__init__.py
beancount_hypothesis/account.py
beancount_hypothesis/common.py
beancount_hypothesis/data.py
beancount_hypothesis/directive.py
beancount_hypothesis/py.typed
beancount_hypothesis-0.1.1.dist-info/LICENSE
beancount_hypothesis-0.1.1.dist-info/WHEEL
beancount_hypothesis-0.1.1.dist-info/METADATA
beancount_hypothesis-0.1.1.dist-info/RECORD
