Metadata-Version: 2.1
Name: beancount-hypothesis
Version: 0.1.1
Summary: A package which provides hypothesis strategies for generating beancount types
Home-page: https://github.com/jmgilman/beancount-hypothesis
License: MIT
Keywords: beancount,hypothesis,testing
Author: Joshua Gilman
Author-email: joshuagilman@gmail.com
Requires-Python: >=3.10,<4.0
Classifier: License :: OSI Approved :: MIT License
Classifier: Programming Language :: Python :: 3
Classifier: Programming Language :: Python :: 3.10
Requires-Dist: RandomWords (>=0.3.0,<0.4.0)
Requires-Dist: beancount (==2.3.4)
Requires-Dist: hypothesis (>=6.36.2,<7.0.0)
Project-URL: Repository, https://github.com/jmgilman/beancount-hypothesis
